{
  "createdAt": "1646899943",
  "creator": "0x9024fe08a7ce0089530265114d5c6c1518aa45b0",
  "currentBalance": "0",
  "handle": "coinfoliodao",
  "id": "512",
  "terminal": "0x981c8ecd009e3e84ee1ff99266bf1461a12e5c68",
  "totalPaid": "0",
  "totalRedeemed": "0",
  "uri": "QmNSRqBtjAT5PfQZ7dc7GiCNeTf1rTNX173xcBddebHZ9L",
  "name": "CoinFolioDAO",
  "infoUri": "www.cresearchlabs.com/coinfoliodao",
  "logoUri": "https://jbx.mypinata.cloud/ipfs/QmZdk6T16reUzJoqjSnDkqbVb4JGzAaBqZ8zjq8P5adPU1",
  "description": "We are builders of decentralized solutions. CoinFolioDAO enables direct access to quality portfolio without the high hurdles and centralization of traditional funds.  Your support backs the development of this decentralize solution for the community.  Your keys, your assets. ",
  "twitter": "CoinFolioDAO ",
  "discord": "https://discord.com/invite/A6K4NURhGh",
  "tokens": [],
  "version": 4,
  "archived": false,
  "payButton": "",
  "payDisclosure": "",
  "fundingCycles": [
    {
      "toETHSymbol": "PEOPLE",
      "target": "0",
      "duration": "Not set ",
      "discount": 0
    }
  ],
  "inWallet": {
    "eth": "0",
    "jbx": "0"
  },
  "tokenAddress": null,
  "totalSupply": "0",
  "holdingSymbol": "Tokens",
  "payEvents": [],
  "redeemEvents": [],
  "withdrawEvents": [],
  "reservesEvents": []
}