{
  "createdAt": "1641557154",
  "creator": "0x65247c038719c178f00097e3508dab9115a2bfb8",
  "currentBalance": "39438877655147",
  "handle": "moon3d",
  "id": "252",
  "terminal": "0xd569d3cce55b71a8a3f3c418c329a66e5f714431",
  "totalPaid": "10000000000000000",
  "totalRedeemed": "0",
  "uri": "QmYcCgdivFC9d7S5QiuGhnU7MyJurx4PAbXFF8mJdCfLHG",
  "name": "Moon3D",
  "infoUri": "https://bit.ly/3JRWIKf",
  "logoUri": "https://jbx.mypinata.cloud/ipfs/QmdrgkBonrRfiCaxBUuG5ezVRWH8pVsQzkHrAkSSYTXKgm",
  "description": "The world's most exciting crypto game, using Ethereum, Bitcoin, and more. To the moon!",
  "twitter": "moon3dio",
  "discord": "https://discord.com/invite/mAnxmC6",
  "tokens": [],
  "version": 3,
  "payButton": "",
  "payDisclosure": "",
  "fundingCycles": [
    {
      "toETHSymbol": "PEOPLE",
      "target": "0",
      "duration": "30 days",
      "start": "3-8-22 12:05pm",
      "end": "4-7-22 12:05pm",
      "discount": 0.1
    }
  ],
  "inWallet": {
    "eth": "0",
    "jbx": "50000000000000000000"
  },
  "tokenAddress": null,
  "totalSupply": "5000000000010000",
  "holdingSymbol": "Tokens",
  "payEvents": [],
  "redeemEvents": [],
  "withdrawEvents": [],
  "reservesEvents": []
}